tatva/__init__.py
tatva/compound.py
tatva/mesh.py
tatva/operator.py
tatva/sparse.py
tatva/element/__init__.py
tatva/element/base.py
tatva/plotting/__init__.py
tatva/plotting/_pyvista.py
tatva-0.3.1.dist-info/METADATA
tatva-0.3.1.dist-info/WHEEL
tatva-0.3.1.dist-info/licenses/COPYING
tatva-0.3.1.dist-info/licenses/COPYING.LESSER
tatva-0.3.1.dist-info/RECORD
