Metadata-Version: 2.4
Name: tatva
Version: 0.3.1
Summary: Lego-like building blocks for finite element analysis
Project-URL: repository, https://gitlab.ethz.ch/smec/software/tatva
Author-email: Mohit Pundir <mpundir@ethz.ch>, Flavio Lorez <florez@ethz.ch>
License-Expression: LGPL-3.0
License-File: COPYING
License-File: COPYING.LESSER
Classifier: Operating System :: OS Independent
Classifier: Programming Language :: Python :: 3
Requires-Python: >=3.10
Requires-Dist: equinox
Requires-Dist: jax-autovmap>=0.3.0
Requires-Dist: jax>=0.4.1
Requires-Dist: numpy
Requires-Dist: sparsejac
Provides-Extra: dev
Requires-Dist: commitizen>=4.9.1; extra == 'dev'
Requires-Dist: pytest>=8.4.2; extra == 'dev'
Provides-Extra: plotting
Requires-Dist: matplotlib; extra == 'plotting'
